deltatextsplitter/Run.py
deltatextsplitter/__init__.py
deltatextsplitter/Source/CompareOutcomes.py
deltatextsplitter/Source/FullRun.py
deltatextsplitter/Source/Human_Readable.py
deltatextsplitter/Source/KPI_Calculation.py
deltatextsplitter/Source/PandasParser.py
deltatextsplitter/Source/StandardRun.py
deltatextsplitter/Source/__init__.py
deltatextsplitter/Source/deltatextsplitter.py
deltatextsplitter/Source/documentclass.py
deltatextsplitter/kpis/__init__.py
deltatextsplitter/kpis/current/__init__.py
deltatextsplitter/outs/__init__.py
deltatextsplitter/pdfs/Cie_working.pdf
deltatextsplitter/pdfs/Decision_Digital_Decade.pdf
deltatextsplitter/pdfs/Directive_Promotion_Energy.pdf
deltatextsplitter/pdfs/Draft regulation deforestation.pdf
deltatextsplitter/pdfs/Proposal deforestation.pdf
deltatextsplitter/pdfs/Proposal_Fit_for_55.pdf
deltatextsplitter/pdfs/Proposal_empowering_consumers.pdf
deltatextsplitter/pdfs/Proposal_greenhouse_gas_emission_reductions.pdf
deltatextsplitter/pdfs/Regulation_greenhouse_gas_emission_reductions.pdf
deltatextsplitter/pdfs/Regulation_trans_European_energy.pdf
deltatextsplitter/pdfs/THESAME_st07592-re04.en22.pdf
deltatextsplitter/pdfs/THESAME_st09111.en22.pdf
deltatextsplitter/pdfs/THESAME_st09585.en22.pdf
deltatextsplitter/pdfs/UNFIT_st05597.en23.pdf
deltatextsplitter/pdfs/UNFIT_st07373.en23.pdf
deltatextsplitter/pdfs/UNFIT_st14322-re01.en22.pdf
deltatextsplitter/pdfs/UNFIT_st14322.en22.pdf
deltatextsplitter/pdfs/UNFIT_st15284.en22.pdf
deltatextsplitter/pdfs/__init__.py
deltatextsplitter/pdfs/st07592-re03.en22.pdf
deltatextsplitter/pdfs/st08328.en23.pdf
deltatextsplitter/refs/Cie_working_references.xlsx
deltatextsplitter/refs/Decision_Digital_Decade_references.xlsx
deltatextsplitter/refs/Directive_Promotion_Energy_references.xlsx
deltatextsplitter/refs/Draft regulation deforestation_references.xlsx
deltatextsplitter/refs/Proposal deforestation_references.xlsx
deltatextsplitter/refs/Proposal_Fit_for_55_references.xlsx
deltatextsplitter-1.1.0.dist-info/LICENSE.txt
deltatextsplitter-1.1.0.dist-info/METADATA
deltatextsplitter-1.1.0.dist-info/WHEEL
deltatextsplitter-1.1.0.dist-info/top_level.txt
deltatextsplitter-1.1.0.dist-info/RECORD
