Metadata-Version: 2.1
Name: deltatextsplitter
Version: 1.1.0
Summary: This packages can efficiently measure the text structure recognition capabilities ofn pdftextsplitter
Home-page: https://gitlab.com/datainnovatielab/public/deltatextsplitter/
Download-URL: https://gitlab.com/datainnovatielab/public/deltatextsplitter/
Author: Unit Data en Innovatie, Ministerie van Infrastructuur en Waterstaat, Netherlands
Author-email: dataloket@minienw.nl
License: MIT
Keywords: NLP,PDF,Text recognition,Structure recognition,ChatGPT
Classifier: Development Status :: 3 - Alpha
Classifier: Intended Audience :: Developers
Classifier: Topic :: Software Development :: Build Tools
Classifier: License :: OSI Approved :: MIT License
Classifier: Programming Language :: Python :: 3.10
Requires-Python: >=3.10
License-File: LICENSE.txt
Requires-Dist: setuptools >=59.6.0
Requires-Dist: wheel >=0.41.1
Requires-Dist: build >=0.10.0
Requires-Dist: numpy >=1.25.2
Requires-Dist: pandas >=2.0.3
Requires-Dist: openpyxl >=3.1.2
Requires-Dist: pytest <=7.4.0,>=7.3.0
Requires-Dist: coverage >=7.3.0
Requires-Dist: pylint >=2.17.5
Requires-Dist: pdftextsplitter >=1.1.0
